fig2q/__init__.py
fig2q/cli.py
fig2q/downloadImage.py
fig2q/helpers.py
fig2q/infographic_config.py
fig2q/scroll_graphic_config.py
Figma_to_Q-0.1.0.dist-info/METADATA
Figma_to_Q-0.1.0.dist-info/WHEEL
Figma_to_Q-0.1.0.dist-info/entry_points.txt
Figma_to_Q-0.1.0.dist-info/top_level.txt
Figma_to_Q-0.1.0.dist-info/RECORD
