Metadata-Version: 2.2
Name: Figma_to_Q
Version: 0.1.0
Summary: A CLI-Tool to publish Figma designs to Q
Home-page: 
Author: Jonas Oesch
Author-email: jonas.oesch@nzz.ch
Classifier: Programming Language :: Python :: 3
Classifier: License :: OSI Approved :: MIT License
Classifier: Operating System :: OS Independent
Requires-Python: >=3.6
Dynamic: author
Dynamic: author-email
Dynamic: classifier
Dynamic: description
Dynamic: description-content-type
Dynamic: requires-python
Dynamic: summary
